LICENSE
MANIFEST.in
README.md
setup.py
hiplot/__init__.py
hiplot/__main__.py
hiplot/experiment.py
hiplot/fetchers.py
hiplot/fetchers_demo.py
hiplot/ipython.py
hiplot/pkginfo.py
hiplot/py.typed
hiplot/render.py
hiplot/server.py
hiplot/test_experiment.py
hiplot/test_fetchers.py
hiplot/test_render.py
hiplot/static/icon-w.svg
hiplot/static/icon.png
hiplot/static/icon.svg
hiplot/static/logo-w.svg
hiplot/static/logo.png
hiplot/static/logo.svg
hiplot/static/thumbnail.png
hiplot/static/built/hiplot.bundle.js
hiplot/static/built/streamlit_component/hiplot_streamlit.bundle.js
hiplot/static/built/streamlit_component/index.html
hiplot/templates/index.html
hiplot_master.egg-info/PKG-INFO
hiplot_master.egg-info/SOURCES.txt
hiplot_master.egg-info/dependency_links.txt
hiplot_master.egg-info/requires.txt
hiplot_master.egg-info/top_level.txt
requirements/dev.txt
requirements/main.txt
scripts/hiplot
scripts/hiplot-render